{
    "race_metadata": {
        "name": "The Stevest",
        "date": "2018-07-28",
        "distance_value": 42,
        "distance_unit": "miles",
        "type": "Road",
        "surface": "Asphalt",
        "course_style": "Loop",
        "start_city": "Concord",
        "start_state": "NC",
        "end_state": "NC",
        "personal_states_covered": [
            "NC"
        ],
        "location_gps": [
            35.32065942156891,
            -80.53571660421157
        ]
    },
    "results": {
        "official_time": "06:14:51",
        "elevation_gain": 2848,
        "elevation_loss": 2828,
        "elevation_unit": "feet",
        "status": "DNF",
        "is_official": false,
        "is_sanctioned": true,
        "team_name": "",
        "personal_legs": [],
        "notes": "Only completed 2 of 3 laps."
    },
    "weather": {
        "temp": null,
        "feels_like": null,
        "humidity": null,
        "wind_speed": null,
        "wind_direction": "",
        "condition": ""
    },
    "rankings": {
        "overall_rank": null,
        "overall_total": null,
        "group_name": "",
        "group_rank": null,
        "group_total": null
    },
    "sources": {
        "original_url": "https://ultrasignup.com/results_event.aspx?did=105111",
        "athlinks_url": "",
        "strava_url": [],
        "local_files": [
            "activity.gpx",
            "results.html",
            "results.png"
        ]
    }
}